caws/__init__.py
caws/main.py
caws-0.2.0.dist-info/licenses/LICENSE
caws-0.2.0.dist-info/METADATA
caws-0.2.0.dist-info/WHEEL
caws-0.2.0.dist-info/entry_points.txt
caws-0.2.0.dist-info/top_level.txt
caws-0.2.0.dist-info/RECORD
