Metadata-Version: 2.4
Name: caws
Version: 0.2.0
Summary: configure AWS responsibly using profile names.
Home-page: https://bitbucket.org/rednap/caws
Author: Andy Klier
Author-email: andyklier@gmail.com
License: MIT
Classifier: Programming Language :: Python :: 3
Classifier: Operating System :: OS Independent
License-File: LICENSE
Requires-Dist: setuptools
Dynamic: author
Dynamic: author-email
Dynamic: classifier
Dynamic: description
Dynamic: description-content-type
Dynamic: home-page
Dynamic: license
Dynamic: license-file
Dynamic: requires-dist
Dynamic: summary
